insider_eda/__init__.py
insider_eda/eda_base.py
insidertrader-0.1.2.dist-info/LICENSE.md
insidertrader-0.1.2.dist-info/METADATA
insidertrader-0.1.2.dist-info/WHEEL
insidertrader-0.1.2.dist-info/top_level.txt
insidertrader-0.1.2.dist-info/RECORD
