Metadata-Version: 2.1
Name: insidertrader
Version: 0.1.2
Summary: A Python package for insider trading analysis
Author: Tuhin Mallick
Author-email: tuhin.mllk@gmail.com
Maintainer: Tuhin Mallick
Maintainer-email: tuhin.mllk@gmail.com
License: OSI Approved :: GNU Affero General Public License v3
Keywords: Insider trading EDA
Classifier: Programming Language :: Python :: 3
Classifier: License :: OSI Approved :: GNU Affero General Public License v3
Classifier: Operating System :: OS Independent
License-File: LICENSE.md
Requires-Dist: matplotlib (>=3.6.2)
Requires-Dist: numpy (>=1.24.0)
Requires-Dist: pandas (>=1.5.2)
Requires-Dist: plotly (>=5.11.0)
Requires-Dist: seaborn (>=0.12.2)
Requires-Dist: statsmodels (>=0.13.5)
